eyja_fastapi/__init__.py
eyja_fastapi/api/__init__.py
eyja_fastapi/api/dynamic_api/__init__.py
eyja_fastapi/api/dynamic_api/model_api.py
eyja_fastapi/api/routes/__init__.py
eyja_fastapi/api/routes/confirm.py
eyja_fastapi/api/routes/current.py
eyja_fastapi/api/routes/login.py
eyja_fastapi/api/routes/logout.py
eyja_fastapi/api/routes/registration.py
eyja_fastapi/api/routes/router.py
eyja_fastapi/decorators/__init__.py
eyja_fastapi/decorators/auth.py
eyja_fastapi/errors/__init__.py
eyja_fastapi/errors/misc_errors.py
eyja_fastapi/errors/user_errors.py
eyja_fastapi/helpers/__init__.py
eyja_fastapi/helpers/models.py
eyja_fastapi/interfaces/__init__.py
eyja_fastapi/interfaces/operators/__init__.py
eyja_fastapi/interfaces/operators/authorized_model_operator.py
eyja_fastapi/middleware/__init__.py
eyja_fastapi/middleware/auth.py
eyja_fastapi/models/__init__.py
eyja_fastapi/models/access_token.py
eyja_fastapi/models/confirm_token.py
eyja_fastapi/models/refresh_token.py
eyja_fastapi/models/user.py
eyja_fastapi/models/user_mixin.py
eyja_fastapi/operators/__init__.py
eyja_fastapi/operators/access_token/__init__.py
eyja_fastapi/operators/access_token/constants.py
eyja_fastapi/operators/access_token/operator.py
eyja_fastapi/operators/confirm_token/__init__.py
eyja_fastapi/operators/confirm_token/constants.py
eyja_fastapi/operators/confirm_token/operator.py
eyja_fastapi/operators/confirm_token/types.py
eyja_fastapi/operators/refresh_token/__init__.py
eyja_fastapi/operators/refresh_token/constants.py
eyja_fastapi/operators/refresh_token/operator.py
eyja_fastapi/operators/refresh_token/statuses.py
eyja_fastapi/operators/user/__init__.py
eyja_fastapi/operators/user/operator.py
eyja_fastapi/processes/__init__.py
eyja_fastapi/processes/auth/__init__.py
eyja_fastapi/processes/auth/authorization.py
eyja_fastapi/processes/auth/confirm.py
eyja_fastapi/processes/auth/refresh.py
eyja_fastapi/processes/auth/registration.py
eyja_fastapi/processes/auth/unauthorization.py
tests/__init__.py
eyja_fastapi-0.2.2.dist-info/METADATA
eyja_fastapi-0.2.2.dist-info/WHEEL
eyja_fastapi-0.2.2.dist-info/top_level.txt
eyja_fastapi-0.2.2.dist-info/zip-safe
eyja_fastapi-0.2.2.dist-info/RECORD
